pyOPCN3logger/__init__.py
pyOPCN3spi/__init__.py
UH_pyOPCN3-0.0.1.dist-info/METADATA
UH_pyOPCN3-0.0.1.dist-info/WHEEL
UH_pyOPCN3-0.0.1.dist-info/top_level.txt
UH_pyOPCN3-0.0.1.dist-info/RECORD
